woo_gemini_query.py
woocommerce_gemini_query-0.1.2.dist-info/licenses/license_file.txt
woocommerce_gemini_query-0.1.2.dist-info/METADATA
woocommerce_gemini_query-0.1.2.dist-info/WHEEL
woocommerce_gemini_query-0.1.2.dist-info/top_level.txt
woocommerce_gemini_query-0.1.2.dist-info/RECORD
