Metadata-Version: 2.4
Name: woocommerce-gemini-query
Version: 0.1.2
License-File: license_file.txt
Dynamic: description
Dynamic: description-content-type
Dynamic: license-file
